<manifest alg="2" build="2018.0.0.379" opt="false" iceEnabled="true" iceMarkupVersion="2" iceEnabledOptions="link,responsive,cachebuster,textStyling" exportTarget="other" domain="predesign.cn" resolutions="1x" timestamp="1684082533710">
  <folder name="css">
    <file name="site_global.css" crc="444006867"/>
    <file name="master_a-__.css" crc="140941347" ref="about-us:gallary:work:index:contact"/>
    <file name="about-us.css" crc="3777926757" ref="about-us"/>
    <file name="gallary.css" crc="4176140644" ref="gallary"/>
    <file name="work.css" crc="4229622614" ref="work"/>
    <file name="index.css" crc="4083839155" ref="index"/>
    <file name="contact.css" crc="426996951" ref="contact"/>
  </folder>
  <folder name="fonts">
    <file name="universnextpro-heavy.woff" crc="3765487321"/>
    <file name="universnextpro-heavy.eot" crc="4260972856"/>
    <file name="方正兰亭黑简体.woff" crc="358034062"/>
    <file name="方正兰亭黑简体.eot" crc="197924486"/>
    <file name="universnextpro-regular.woff" crc="4035086773"/>
    <file name="universnextpro-regular.eot" crc="172348008"/>
    <file name="方正兰亭黑简体-bold.woff" crc="383011104"/>
    <file name="方正兰亭黑简体-bold.eot" crc="4196065648"/>
    <file name="universnextpro-blod.woff" crc="351243697"/>
    <file name="universnextpro-bold.eot" crc="4087606172"/>
    <file name="universnextpro-light.woff" crc="143263625"/>
    <file name="universnextpro-light.eot" crc="387407359"/>
  </folder>
  <folder name="scripts">
    <file name="jquery-1.8.3.min.js" crc="209076791" ref="index:work:gallary:about-us:contact"/>
    <file name="museutils.js" crc="3803043152" ref="index:work:gallary:about-us:contact"/>
    <file name="whatinput.js" crc="86476730" ref="index:work:gallary:about-us:contact"/>
    <file name="museconfig.js" crc="380897831" ref="index:work:gallary:about-us:contact"/>
    <file name="jquery.watch.js" crc="99325471" ref="index:work:gallary:about-us:contact"/>
    <file name="require.js" crc="4157109226" ref="index:work:gallary:about-us:contact"/>
  </folder>
  <folder name="images">
    <file name="logo_black.svg" crc="4237635692" seo="true" ref="index:work:gallary:about-us:contact">
      <caption webpage="index" alt=""/>
      <caption webpage="work" alt=""/>
      <caption webpage="about-us" alt=""/>
      <caption webpage="gallary" alt=""/>
      <caption webpage="contact" alt=""/>
    </file>
    <file name="logo_black_poster_.png" crc="3874940372" ref="index"/>
    <file name="blank.gif" crc="4208392903" ref="index"/>
    <file name="webdesign_works_black.svg" crc="4242725139" seo="true" ref="index:work:gallary:about-us:contact">
      <caption webpage="index" alt=""/>
      <caption webpage="work" alt=""/>
      <caption webpage="about-us" alt=""/>
      <caption webpage="gallary" alt=""/>
      <caption webpage="contact" alt=""/>
    </file>
    <file name="webdesign_works_black_poster_.png" crc="411735059" ref="index"/>
    <file name="webdesign_gallary_black.svg" crc="349745142" seo="true" ref="index:work:gallary:about-us:contact">
      <caption webpage="index" alt=""/>
      <caption webpage="work" alt=""/>
      <caption webpage="about-us" alt=""/>
      <caption webpage="gallary" alt=""/>
      <caption webpage="contact" alt=""/>
    </file>
    <file name="webdesign_gallary_black_poster_.png" crc="4194955107" ref="index"/>
    <file name="webdesign_about_black.svg" crc="3781214409" seo="true" ref="index:work:gallary:about-us:contact">
      <caption webpage="index" alt=""/>
      <caption webpage="work" alt=""/>
      <caption webpage="about-us" alt=""/>
      <caption webpage="gallary" alt=""/>
      <caption webpage="contact" alt=""/>
    </file>
    <file name="webdesign_about_black_poster_.png" crc="496244795" ref="index"/>
    <file name="2.jpg" crc="4093261442" seo="true" ref="work">
      <caption webpage="work" alt=""/>
    </file>
    <file name="g-crop-u1526.jpg" crc="3960188817" seo="true" ref="work">
      <caption webpage="work" alt=""/>
    </file>
    <file name="s4-crop-u1581.jpg" crc="4019101127" seo="true" ref="work">
      <caption webpage="work" alt=""/>
    </file>
    <file name="b.jpg" crc="4094470611" seo="true" ref="work">
      <caption webpage="work" alt=""/>
    </file>
    <file name="h-crop-u1533.jpg" crc="3838037750" seo="true" ref="work">
      <caption webpage="work" alt=""/>
    </file>
    <file name="h-crop-u1574.jpg" crc="3838037750" seo="true" ref="work">
      <caption webpage="work" alt=""/>
    </file>
    <file name="71_what should i do_宁宁rgb-crop-u1325.jpg" crc="4132704849" seo="true" ref="gallary">
      <caption webpage="gallary" alt=""/>
    </file>
    <file name="8-crop-u1339.jpg" crc="4156293355" seo="true" ref="gallary">
      <caption webpage="gallary" alt=""/>
    </file>
    <file name="20200812_禁止掉头-crop-u1351.jpg" crc="4109873969" seo="true" ref="gallary">
      <caption webpage="gallary" alt=""/>
    </file>
    <file name="001 (2)-crop-u1003.jpg" crc="83068861" seo="true" ref="gallary">
      <caption webpage="gallary" alt=""/>
    </file>
    <file name="wall_poster3-crop-u1342.jpg" crc="3991125670" seo="true" ref="gallary">
      <caption webpage="gallary" alt=""/>
    </file>
    <file name="3.jpg" crc="259561514" seo="true" ref="gallary">
      <caption webpage="gallary" alt=""/>
    </file>
    <file name="虚拟形象-46-crop-u514.jpg" crc="108277589" seo="true" ref="about-us">
      <caption webpage="about-us" alt=""/>
    </file>
  </folder>
  <file name="index.html" crc="3946135881" seo="true" mt="1684082060056" redirect="true"/>
  <file name="work.html" crc="4112291749" seo="true" mt="1684082301542" redirect="true"/>
  <file name="gallary.html" crc="3975259029" seo="true" mt="1684082400524" redirect="true"/>
  <file name="about-us.html" crc="4166479864" seo="true" mt="1684056808284" redirect="true"/>
  <file name="contact.html" crc="4252391797" seo="true" mt="1684056808284" redirect="true"/>
</manifest>